hooks/__init__.py
hooks/__main__.py
hooks/_version.py
hooks/commit-msg
hooks/get_msg.py
hooks/get_repo.py
hooks/pre-commit
hooks/prepare-commit-msg
hooks/requirements-current-3.6.txt
hooks/requirements-current-3.7.txt
hooks/requirements-current-3.8.txt
hooks/versioneer.py
hooks/get_jira/__init__.py
hooks/get_jira/get_auth.py
hooks/get_jira/get_jira.py
hooks/tests/__init__.py
hooks/tests/pytest_test.py
nabla/README.md
nabla/__init__.py
nabla/main.py
nabla/api/__init__.py
nabla/api/ping.py
nabla/api/v1.py
tests/.pre-commit-config.yaml
tests/__init__.py
tests/check_certificates.py
tests/init.sh
tests/pytest.sh
tests/test.sh
tests/test_nabla_version.py
tests/test_package.py
tests/test_sample.sh
tests/test_unittest.py
tests/version.sh
tests/unit/test_api.py
nabla_hooks-1.0.5.dist-info/LICENSE
nabla_hooks-1.0.5.dist-info/METADATA
nabla_hooks-1.0.5.dist-info/WHEEL
nabla_hooks-1.0.5.dist-info/top_level.txt
nabla_hooks-1.0.5.dist-info/RECORD
