Metadata-Version: 2.1
Name: nabla-hooks
Version: 1.0.5
Summary: Hook to validate branch name and issue
Home-page: https://github.com/AlbanAndrieu/nabla-hooks
Author: Alban Andrieu
Author-email: "Andrieu, Alban" <alban.andrieu@free.fr>
Maintainer: Alban Andrieu
Maintainer-email: alban.andrieu@free.fr
License: MIT
Requires-Python: >=3.10
License-File: LICENSE
Requires-Dist: dynamic
